ArraySplitter/__init__.py
ArraySplitter/classify.py
ArraySplitter/decompose.py
ArraySplitter/extract.py
ArraySplitter/main.py
ArraySplitter/rotate.py
ArraySplitter/core_functions/__init__.py
ArraySplitter/core_functions/io/__init__.py
ArraySplitter/core_functions/io/block_file.py
ArraySplitter/core_functions/io/fasta_reader.py
ArraySplitter/core_functions/io/satellome_reader.py
ArraySplitter/core_functions/io/tab_file.py
ArraySplitter/core_functions/io/trf_reader.py
ArraySplitter/core_functions/models/__init__.py
ArraySplitter/core_functions/models/trf_model.py
ArraySplitter/core_functions/tools/__init__.py
ArraySplitter/core_functions/tools/anchor_graph.py
ArraySplitter/core_functions/tools/fs_tree.py
ArraySplitter/core_functions/tools/parsers.py
ArraySplitter/core_functions/tools/rotation.py
ArraySplitter/core_functions/tools/sequences.py
arraysplitter-1.3.0.dist-info/licenses/LICENSE
arraysplitter-1.3.0.dist-info/METADATA
arraysplitter-1.3.0.dist-info/WHEEL
arraysplitter-1.3.0.dist-info/entry_points.txt
arraysplitter-1.3.0.dist-info/top_level.txt
arraysplitter-1.3.0.dist-info/RECORD
